{"jobs":[{"name":"awareness-check","runs":196,"successes":196,"failures":0,"totalCost":0,"lastRun":"2026-04-10T19:05:06Z"},{"name":"connections-brainstorm","runs":12,"successes":12,"failures":0,"totalCost":0.0261,"lastRun":"2026-04-10T09:00:51Z"},{"name":"daily-attention","runs":582,"successes":582,"failures":0,"totalCost":1.9604,"lastRun":"2026-04-10T19:13:16Z"},{"name":"email-triage","runs":274,"successes":241,"failures":33,"totalCost":0.28090000000000026,"lastRun":"2026-04-10T16:37:06Z"},{"name":"overnight-research","runs":13,"successes":11,"failures":0,"totalCost":0.066,"lastRun":"2026-04-10T03:25:50Z"},{"name":"vault-health","runs":6,"successes":3,"failures":3,"totalCost":0,"lastRun":"2026-04-10T06:06:58Z"}],"totalCostToday":0.3687,"totalCostWeek":2.333399999999999,"costCeiling":5.00,"lastUpdated":"2026-04-10T19:30:45Z"}
